img/__init__.py
img/segment_aa.svg
img/segment_ab.svg
img/segment_ba.svg
img/segment_bb.svg
pyacptrak/__init__.py
pyacptrak/pyacptrak.py
pyacptrak/img/__init__.py
pyacptrak/img/segment_aa.svg
pyacptrak/img/segment_ab - Copy.svg
pyacptrak/img/segment_ab.svg
pyacptrak/img/segment_ba.svg
pyacptrak/img/segment_bb.svg
pyacptrak-0.0.6.dist-info/LICENSE
pyacptrak-0.0.6.dist-info/METADATA
pyacptrak-0.0.6.dist-info/WHEEL
pyacptrak-0.0.6.dist-info/top_level.txt
pyacptrak-0.0.6.dist-info/RECORD
