Metadata-Version: 2.1
Name: pyacptrak
Version: 0.0.6
Summary: Create ACOPOStrak resources for projects, training, meetings, mappView widgets, etc...
Home-page: https://github.com/HeytalePazguato/pyacptrak
Author: HeytalePazguato (Jorge Centeno)
Author-email: Heytale.Pazguato@gmail.com
Maintainer: HeytalePazguato
Project-URL: Bug Tracker, https://github.com/HeytalePazguato/pyacptrak/issues
Classifier: Programming Language :: Python :: 3
Classifier: Programming Language :: Python :: 3.9
Classifier: Programming Language :: Python :: 3.10
Classifier: License :: OSI Approved :: GNU General Public License v3 (GPLv3)
Classifier: Operating System :: OS Independent
Requires-Python: >=3.9
License-File: LICENSE
Requires-Dist: svgwrite (>=1.4.0)
Requires-Dist: xmltodict (>=0.12.0)
Requires-Dist: numpy (>=1.22.3)
Requires-Dist: typeguard (>=2.13.3)
Requires-Dist: IPython (>=7.23.1)
Requires-Dist: typing (>=3.7)
Provides-Extra: dev
Requires-Dist: pytest (>=7.1) ; extra == 'dev'
